cli/__init__.py
cli/interpreter.py
cli/stocktrack.py
cli/strategy_tester.py
cli/texteditor.py
tests/__init__.py
tests/stocktrack_backtest_test.py
stocktrack-1.1.1.dist-info/METADATA
stocktrack-1.1.1.dist-info/WHEEL
stocktrack-1.1.1.dist-info/entry_points.txt
stocktrack-1.1.1.dist-info/top_level.txt
stocktrack-1.1.1.dist-info/RECORD
