Metadata-Version: 2.1
Name: stocktrack
Version: 1.1.1
Requires-Dist: click
Requires-Dist: requests
Requires-Dist: pandas
Requires-Dist: matplotlib
Requires-Dist: colorama
Requires-Dist: gedit
